{
    "model": {
        "0": ["1-12(5)", "2-12(5)", "3-12(5)", "4-12(5)",
              "5-12(5)", "6-12(5)", "7-12(5)", "8-12(5)",
              "9-12(5)", "10-12(5)", "11-12(5)", "12-12(5)",
              "13-12(5)", "14-12(5)", "15-12(5)", "16-12(5)"],

        "1": ["1-12(5c)", "2-12(5c)", "3-12(5c)", "4-12(5c)",
              "5-12(5c)", "6-12(5c)", "7-12(5c)", "8-12(5c)",
              "9-12(5c)", "10-12(5c)", "11-12(5c)", "12-12(5c)",
              "13-12(5c)", "14-12(5c)", "15-12(5c)", "16-12(5c)"],

        "2": ["1-12(5s)", "2-12(5s)", "3-12(5s)", "4-12(5s)",
              "5-12(5s)", "6-12(5s)", "7-12(5s)", "8-12(5s)",
              "9-12(5s)", "10-12(5s)", "11-12(5s)", "12-12(5s)",
              "13-12(5s)", "14-12(5s)", "15-12(5s)", "16-12(5s)"],

        "3": ["1-12(SE)", "2-12(SE)", "3-12(SE)", "4-12(SE)",
              "5-12(SE)", "6-12(SE)", "7-12(SE)", "8-12(SE)",
              "9-12(SE)", "10-12(SE)", "11-12(SE)", "12-12(SE)",
              "13-12(SE)", "14-12(SE)", "15-12(SE)", "16-12(SE)"],

        "4": ["1-12(6)", "2-12(6)", "3-12(6)", "4-12(6)",
              "5-12(6)", "6-12(6)", "7-12(6)", "8-12(6)",
              "9-12(6)", "10-12(6)", "11-12(6)", "12-12(6)",
              "13-12(6)", "14-12(6)", "15-12(6)", "16-12(6)"],

        "5": ["1-12(6P)", "2-12(6P)", "3-12(6P)", "4-12(6P)",
              "5-12(6P)", "6-12(6P)", "7-12(6P)", "8-12(6P)",
              "9-12(6P)", "10-12(6P)", "11-12(6P)", "12-12(6P)",
              "13-12(6P)", "14-12(6P)", "15-12(6P)", "16-12(6P)"],

        "6": ["1-12(6s)", "2-12(6s)", "3-12(6s)", "4-12(6s)",
              "5-12(6s)", "6-12(6s)", "7-12(6s)", "8-12(6s)",
              "9-12(6s)", "10-12(6s)", "11-12(6s)", "12-12(6s)",
              "13-12(6s)", "14-12(6s)", "15-12(6s)", "16-12(6s)"],

        "7": ["1-12(6sP)", "2-12(6sP)", "3-12(6sP)", "4-12(6sP)",
              "5-12(6sP)", "6-12(6sP)", "7-12(6sP)", "8-12(6sP)",
              "9-12(6sP)", "10-12(6sP)", "11-12(6sP)", "12-12(6sP)",
              "13-12(6sP)", "14-12(6sP)", "15-12(6sP)", "16-12(6sP)"],

        "8": ["1-12(7)", "2-12(7)", "3-12(7)", "4-12(7)",
              "5-12(7)", "6-12(7)", "7-12(7)", "8-12(7)",
              "9-12(7)", "10-12(7)", "11-12(7)", "12-12(7)",
              "13-12(7)", "14-12(7)", "15-12(7)", "16-12(7)"],

        "9": ["1-12(7P)", "2-12(7P)", "3-12(7P)", "4-12(7P)",
              "5-12(7P)", "6-12(7P)", "7-12(7P)", "8-12(7P)",
              "9-12(7P)", "10-12(7P)", "11-12(7P)", "12-12(7P)",
              "13-12(7P)", "14-12(7P)", "15-12(7P)", "16-12(7P)"],

        "10": ["1-12(8)", "2-12(8)", "3-12(8)", "4-12(8)",
              "5-12(8)", "6-12(8)", "7-12(8)", "8-12(8)",
              "9-12(8)", "10-12(8)", "11-12(8)", "12-12(8)",
              "13-12(8)", "14-12(8)", "15-12(8)", "16-12(8)"],

        "11": ["1-12(8P)", "2-12(8P)", "3-12(8P)", "4-12(8P)",
              "5-12(8P)", "6-12(8P)", "7-12(8P)", "8-12(8P)",
              "9-12(8P)", "10-12(8P)", "11-12(8P)", "12-12(8P)",
              "13-12(8P)", "14-12(8P)", "15-12(8P)", "16-12(8P)"],

        "12": ["1-12(X)", "2-12(X)", "3-12(X)", "4-12(X)",
              "5-12(X)", "6-12(X)", "7-12(X)", "8-12(X)",
              "9-12(X)", "10-12(X)", "11-12(X)", "12-12(X)",
              "13-12(X)", "14-12(X)", "15-12(X)", "16-12(X)"],

        "13": ["1-12(Xr)", "2-12(Xr)", "3-12(Xr)", "4-12(Xr)",
              "5-12(Xr)", "6-12(Xr)", "7-12(Xr)", "8-12(Xr)",
              "9-12(Xr)", "10-12(Xr)", "11-12(Xr)", "12-12(Xr)",
              "13-12(Xr)", "14-12(Xr)", "15-12(Xr)", "16-12(Xr)"],

        "14": ["1-12(Xs)", "2-12(Xs)", "3-12(Xs)", "4-12(Xs)",
              "5-12(Xs)", "6-12(Xs)", "7-12(Xs)", "8-12(Xs)",
              "9-12(Xs)", "10-12(Xs)", "11-12(Xs)", "12-12(Xs)",
              "13-12(Xs)", "14-12(Xs)", "15-12(Xs)", "16-12(Xs)"],

        "15": ["1-12(Xs Max)", "2-12(Xs Max)", "3-12(Xs Max)", "4-12(Xs Max)",
              "5-12(Xs Max)", "6-12(Xs Max)", "7-12(Xs Max)", "8-12(Xs Max)",
              "9-12(Xs Max)", "10-12(Xs Max)", "11-12(Xs Max)", "12-12(Xs Max)",
              "13-12(Xs Max)", "14-12(Xs Max)", "15-12(Xs Max)", "16-12(Xs Max)"]
    }
}